{"name": "Class BasicInternalFrameTitlePane", "module": "java.desktop", "package": "javax.swing.plaf.basic", "text": "The class that manages a basic title bar\n \nWarning:\n Serialized objects of this class will not be compatible with\n future Swing releases. The current serialization support is\n appropriate for short term storage or RMI between applications running\n the same version of Swing.  As of 1.4, support for long term storage\n of all JavaBeans\u2122\n has been added to the java.beans package.\n Please see XMLEncoder.", "codes": ["public class BasicInternalFrameTitlePane\nextends JComponent"], "fields": [{"field_name": "menuBar", "field_sig": "protected\u00a0JMenuBar menuBar", "description": "The instance of JMenuBar."}, {"field_name": "iconButton", "field_sig": "protected\u00a0JButton iconButton", "description": "The iconify button."}, {"field_name": "maxButton", "field_sig": "protected\u00a0JButton maxButton", "description": "The maximize button."}, {"field_name": "closeButton", "field_sig": "protected\u00a0JButton closeButton", "description": "The close button."}, {"field_name": "windowMenu", "field_sig": "protected\u00a0JMenu windowMenu", "description": "The instance of JMenu."}, {"field_name": "frame", "field_sig": "protected\u00a0JInternalFrame frame", "description": "The instance of JInternalFrame."}, {"field_name": "selectedTitleColor", "field_sig": "protected\u00a0Color selectedTitleColor", "description": "The color of a selected title."}, {"field_name": "selectedTextColor", "field_sig": "protected\u00a0Color selectedTextColor", "description": "The color of a selected text."}, {"field_name": "notSelectedTitleColor", "field_sig": "protected\u00a0Color notSelectedTitleColor", "description": "The color of a not selected title."}, {"field_name": "notSelectedTextColor", "field_sig": "protected\u00a0Color notSelectedTextColor", "description": "The color of a not selected text."}, {"field_name": "maxIcon", "field_sig": "protected\u00a0Icon maxIcon", "description": "The maximize icon."}, {"field_name": "minIcon", "field_sig": "protected\u00a0Icon minIcon", "description": "The minimize icon."}, {"field_name": "iconIcon", "field_sig": "protected\u00a0Icon iconIcon", "description": "The iconify icon."}, {"field_name": "closeIcon", "field_sig": "protected\u00a0Icon closeIcon", "description": "The close icon."}, {"field_name": "propertyChangeListener", "field_sig": "protected\u00a0PropertyChangeListener propertyChangeListener", "description": "The instance of a PropertyChangeListener."}, {"field_name": "closeAction", "field_sig": "protected\u00a0Action closeAction", "description": "The instance of a CloseAction."}, {"field_name": "maximizeAction", "field_sig": "protected\u00a0Action maximizeAction", "description": "The instance of a MaximizeAction."}, {"field_name": "iconifyAction", "field_sig": "protected\u00a0Action iconifyAction", "description": "The instance of an IconifyAction."}, {"field_name": "restoreAction", "field_sig": "protected\u00a0Action restoreAction", "description": "The instance of a RestoreAction."}, {"field_name": "moveAction", "field_sig": "protected\u00a0Action moveAction", "description": "The instance of a MoveAction."}, {"field_name": "sizeAction", "field_sig": "protected\u00a0Action sizeAction", "description": "The instance of a SizeAction."}, {"field_name": "CLOSE_CMD", "field_sig": "protected static final\u00a0String CLOSE_CMD", "description": "The close button text property."}, {"field_name": "ICONIFY_CMD", "field_sig": "protected static final\u00a0String ICONIFY_CMD", "description": "The minimize button text property."}, {"field_name": "RESTORE_CMD", "field_sig": "protected static final\u00a0String RESTORE_CMD", "description": "The restore button text property."}, {"field_name": "MAXIMIZE_CMD", "field_sig": "protected static final\u00a0String MAXIMIZE_CMD", "description": "The maximize button text property."}, {"field_name": "MOVE_CMD", "field_sig": "protected static final\u00a0String MOVE_CMD", "description": "The move button text property."}, {"field_name": "SIZE_CMD", "field_sig": "protected static final\u00a0String SIZE_CMD", "description": "The size button text property."}], "methods": [{"method_name": "installTitlePane", "method_sig": "protected void installTitlePane()", "description": "Installs the title pane."}, {"method_name": "addSubComponents", "method_sig": "protected void addSubComponents()", "description": "Adds subcomponents."}, {"method_name": "createActions", "method_sig": "protected void createActions()", "description": "Creates actions."}, {"method_name": "installListeners", "method_sig": "protected void installListeners()", "description": "Registers listeners."}, {"method_name": "uninstallListeners", "method_sig": "protected void uninstallListeners()", "description": "Unregisters listeners."}, {"method_name": "installDefaults", "method_sig": "protected void installDefaults()", "description": "Installs default properties."}, {"method_name": "uninstallDefaults", "method_sig": "protected void uninstallDefaults()", "description": "Uninstalls default properties."}, {"method_name": "createButtons", "method_sig": "protected void createButtons()", "description": "Creates buttons."}, {"method_name": "setButtonIcons", "method_sig": "protected void setButtonIcons()", "description": "Sets the button icons."}, {"method_name": "assembleSystemMenu", "method_sig": "protected void assembleSystemMenu()", "description": "Assembles system menu."}, {"method_name": "addSystemMenuItems", "method_sig": "protected void addSystemMenuItems (JMenu systemMenu)", "description": "Adds system menu items to systemMenu."}, {"method_name": "createSystemMenu", "method_sig": "protected JMenu createSystemMenu()", "description": "Returns a new instance of JMenu."}, {"method_name": "createSystemMenuBar", "method_sig": "protected JMenuBar createSystemMenuBar()", "description": "Returns a new instance of JMenuBar."}, {"method_name": "showSystemMenu", "method_sig": "protected void showSystemMenu()", "description": "Shows system menu."}, {"method_name": "paintTitleBackground", "method_sig": "protected void paintTitleBackground (Graphics g)", "description": "Invoked from paintComponent.\n Paints the background of the titlepane.  All text and icons will\n then be rendered on top of this background."}, {"method_name": "getTitle", "method_sig": "protected String getTitle (String text,\n                          FontMetrics fm,\n                          int availTextWidth)", "description": "Returns the title."}, {"method_name": "postClosingEvent", "method_sig": "protected void postClosingEvent (JInternalFrame frame)", "description": "Post a WINDOW_CLOSING-like event to the frame, so that it can\n be treated like a regular Frame."}, {"method_name": "enableActions", "method_sig": "protected void enableActions()", "description": "Enables actions."}, {"method_name": "createPropertyChangeListener", "method_sig": "protected PropertyChangeListener createPropertyChangeListener()", "description": "Returns an instance of PropertyChangeListener."}, {"method_name": "createLayout", "method_sig": "protected LayoutManager createLayout()", "description": "Returns a layout manager."}]}