{"name": "Class BasicRadioButtonMenuItemUI", "module": "java.desktop", "package": "javax.swing.plaf.basic", "text": "BasicRadioButtonMenuItem implementation", "codes": ["public class BasicRadioButtonMenuItemUI\nextends BasicMenuItemUI"], "fields": [], "methods": [{"method_name": "createUI", "method_sig": "public static ComponentUI createUI (JComponent b)", "description": "Returns a new instance of BasicRadioButtonMenuItemUI."}, {"method_name": "processMouseEvent", "method_sig": "public void processMouseEvent (JMenuItem item,\n                              MouseEvent e,\n                              MenuElement[] path,\n                              MenuSelectionManager manager)", "description": "Invoked when mouse event occurs."}]}