{"name": "Interface BeanContextServiceRevokedListener", "module": "java.desktop", "package": "java.beans.beancontext", "text": "The listener interface for receiving\n BeanContextServiceRevokedEvent objects. A class that is\n interested in processing a BeanContextServiceRevokedEvent\n implements this interface.", "codes": ["public interface BeanContextServiceRevokedListener\nextends EventListener"], "fields": [], "methods": [{"method_name": "serviceRevoked", "method_sig": "void serviceRevoked (BeanContextServiceRevokedEvent bcsre)", "description": "The service named has been revoked. getService requests for\n this service will no longer be satisfied."}]}