{"name": "Class DateFormatter", "module": "java.desktop", "package": "javax.swing.text", "text": "DateFormatter is an InternationalFormatter that does its\n formatting by way of an instance of java.text.DateFormat.\n \nWarning:\n Serialized objects of this class will not be compatible with\n future Swing releases. The current serialization support is\n appropriate for short term storage or RMI between applications running\n the same version of Swing.  As of 1.4, support for long term storage\n of all JavaBeans\u2122\n has been added to the java.beans package.\n Please see XMLEncoder.", "codes": ["public class DateFormatter\nextends InternationalFormatter"], "fields": [], "methods": [{"method_name": "setFormat", "method_sig": "public void setFormat (DateFormat format)", "description": "Sets the format that dictates the legal values that can be edited\n and displayed.\n \n If you have used the nullary constructor the value of this property\n will be determined for the current locale by way of the\n Dateformat.getDateInstance() method."}]}