{"name": "Class DateTimeParseException", "module": "java.base", "package": "java.time.format", "text": "An exception thrown when an error occurs during parsing.\n \n This exception includes the text being parsed and the error index.", "codes": ["public class DateTimeParseException\nextends DateTimeException"], "fields": [], "methods": [{"method_name": "getParsedString", "method_sig": "public String getParsedString()", "description": "Returns the string that was being parsed."}, {"method_name": "getErrorIndex", "method_sig": "public int getErrorIndex()", "description": "Returns the index where the error was found."}]}