{"name": "Class DeflaterOutputStream", "module": "java.base", "package": "java.util.zip", "text": "This class implements an output stream filter for compressing data in\n the \"deflate\" compression format. It is also used as the basis for other\n types of compression filters, such as GZIPOutputStream.", "codes": ["public class DeflaterOutputStream\nextends FilterOutputStream"], "fields": [{"field_name": "def", "field_sig": "protected\u00a0Deflater def", "description": "Compressor for this stream."}, {"field_name": "buf", "field_sig": "protected\u00a0byte[] buf", "description": "Output buffer for writing compressed data."}], "methods": [{"method_name": "write", "method_sig": "public void write (int b)\n           throws IOException", "description": "Writes a byte to the compressed output stream. This method will\n block until the byte can be written."}, {"method_name": "write", "method_sig": "public void write (byte[] b,\n                  int off,\n                  int len)\n           throws IOException", "description": "Writes an array of bytes to the compressed output stream. This\n method will block until all the bytes are written."}, {"method_name": "finish", "method_sig": "public void finish()\n            throws IOException", "description": "Finishes writing compressed data to the output stream without closing\n the underlying stream. Use this method when applying multiple filters\n in succession to the same output stream."}, {"method_name": "close", "method_sig": "public void close()\n           throws IOException", "description": "Writes remaining compressed data to the output stream and closes the\n underlying stream."}, {"method_name": "deflate", "method_sig": "protected void deflate()\n                throws IOException", "description": "Writes next block of compressed data to the output stream."}, {"method_name": "flush", "method_sig": "public void flush()\n           throws IOException", "description": "Flushes the compressed output stream.\n\n If syncFlush is true when this compressed output stream is\n constructed, this method first flushes the underlying compressor\n with the flush mode Deflater.SYNC_FLUSH to force\n all pending data to be flushed out to the output stream and then\n flushes the output stream. Otherwise this method only flushes the\n output stream without flushing the compressor."}]}