{"name": "Interface DHPrivateKey", "module": "java.base", "package": "javax.crypto.interfaces", "text": "The interface to a Diffie-Hellman private key.", "codes": ["public interface DHPrivateKey\nextends DHKey, PrivateKey"], "fields": [{"field_name": "serialVersionUID", "field_sig": "static final\u00a0long serialVersionUID", "description": "The class fingerprint that is set to indicate serialization\n compatibility since J2SE 1.4."}], "methods": [{"method_name": "getX", "method_sig": "BigInteger getX()", "description": "Returns the private value, x."}]}