{"name": "Interface DocTree", "module": "jdk.compiler", "package": "com.sun.source.doctree", "text": "Common interface for all nodes in a documentation syntax tree.", "codes": ["public interface DocTree"], "fields": [], "methods": [{"method_name": "getKind", "method_sig": "DocTree.Kind getKind()", "description": "Returns the kind of this tree."}, {"method_name": "accept", "method_sig": "<R, D> R accept (DocTreeVisitor<R, D> visitor,\n                     D data)", "description": "Accept method used to implement the visitor pattern.  The\n visitor pattern is used to implement operations on trees."}]}