{"name": "Class EventTypeInfo", "module": "jdk.management.jfr", "package": "jdk.management.jfr", "text": "Management representation of an EventType.", "codes": ["public final class EventTypeInfo\nextends Object"], "fields": [], "methods": [{"method_name": "getLabel", "method_sig": "public String getLabel()", "description": "Returns the label, a human-readable name, associated with the event type\n for this EventTypeInfo (for example, \"Garbage Collection\")."}, {"method_name": "getCategoryNames", "method_sig": "public List<String> getCategoryNames()", "description": "Returns the list of human-readable names that makes up the category for this\n EventTypeInfo (for example, \"Java Virtual Machine\" or \"Garbage Collector\")."}, {"method_name": "getId", "method_sig": "public long getId()", "description": "Returns the unique ID for the event type associated with this\n EventTypeInfo, not guaranteed to be the same for different Java\n Virtual Machines (JVMs) instances."}, {"method_name": "getName", "method_sig": "public String getName()", "description": "Returns the name for the event type associated with this\n EventTypeInfo (for example, \"jdk.GarbageCollection\")."}, {"method_name": "getDescription", "method_sig": "public String getDescription()", "description": "Returns a short sentence or two describing the event type associated with\n this EventTypeInfo, for example\n \"Garbage collection performed by the JVM\"\"."}, {"method_name": "getSettingDescriptors", "method_sig": "public List<SettingDescriptorInfo> getSettingDescriptors()", "description": "Returns settings for the event type associated with this\n EventTypeInfo."}, {"method_name": "toString", "method_sig": "public String toString()", "description": "Returns a description of this EventTypeInfo."}, {"method_name": "from", "method_sig": "public static EventTypeInfo from (CompositeData cd)", "description": "Returns an EventType represented by the specified\n CompositeData\n\n The supplied CompositeData must have the following item names and\n item types to be valid. \n\nThe name and type the specified CompositeData must contain\n\n\nName\nType\n\n\n\n\nid\nLong\n\n\nname\nString\n\n\nlabel\nString\n\n\ndescription\nString\n\n\ncategory\nArrayType(1, SimpleType.STRING)\n\n\nsettings\njavax.management.openmbean.CompositeData[] whose element type\n is the mapped type for SettingDescriptorInfo as specified in the\n SettingDescriptorInfo.from(javax.management.openmbean.CompositeData) method.\n\n\n\n"}]}