{"name": "Class GeoTIFFTagSet", "module": "java.desktop", "package": "javax.imageio.plugins.tiff", "text": "A class representing the tags found in a GeoTIFF IFD.  GeoTIFF is a\n standard for annotating georeferenced or geocoded raster imagery.\n This class does not handle the GeoKeys referenced\n from a GeoKeyDirectoryTag as those are not TIFF tags per se.\n\n The definitions of the data types referenced by the field\n definitions may be found in the TIFFTag class.", "codes": ["public final class GeoTIFFTagSet\nextends TIFFTagSet"], "fields": [{"field_name": "TAG_MODEL_PIXEL_SCALE", "field_sig": "public static final\u00a0int TAG_MODEL_PIXEL_SCALE", "description": "A tag used to specify the size of raster pixel spacing in\n model space units."}, {"field_name": "TAG_MODEL_TRANSFORMATION", "field_sig": "public static final\u00a0int TAG_MODEL_TRANSFORMATION", "description": "A tag used to specify the transformation matrix between the raster\n space and the model space."}, {"field_name": "TAG_MODEL_TIE_POINT", "field_sig": "public static final\u00a0int TAG_MODEL_TIE_POINT", "description": "A tag used to store raster-to-model tiepoint pairs."}, {"field_name": "TAG_GEO_KEY_DIRECTORY", "field_sig": "public static final\u00a0int TAG_GEO_KEY_DIRECTORY", "description": "A tag used to store the GeoKey directory."}, {"field_name": "TAG_GEO_DOUBLE_PARAMS", "field_sig": "public static final\u00a0int TAG_GEO_DOUBLE_PARAMS", "description": "A tag used to store all double-values GeoKeys."}, {"field_name": "TAG_GEO_ASCII_PARAMS", "field_sig": "public static final\u00a0int TAG_GEO_ASCII_PARAMS", "description": "A tag used to store all ASCII-values GeoKeys."}], "methods": [{"method_name": "getInstance", "method_sig": "public static GeoTIFFTagSet getInstance()", "description": "Returns a shared instance of a GeoTIFFTagSet."}]}