{"name": "Interface IntersectionType", "module": "java.compiler", "package": "javax.lang.model.type", "text": "Represents an intersection type.\n\n An intersection type can be either implicitly or explicitly\n declared in a program. For example, the bound of the type parameter\n <T extends Number & Runnable> is an (implicit) intersection\n type.  This is represented by an IntersectionType with\n Number and Runnable as its bounds.", "codes": ["public interface IntersectionType\nextends TypeMirror"], "fields": [], "methods": [{"method_name": "getBounds", "method_sig": "List<? extends TypeMirror> getBounds()", "description": "Return the bounds comprising this intersection type."}]}