{"name": "Class JTree.TreeSelectionRedirector", "module": "java.desktop", "package": "javax.swing", "text": "Handles creating a new TreeSelectionEvent with the\n JTree as the\n source and passing it off to all the listeners.\n \nWarning:\n Serialized objects of this class will not be compatible with\n future Swing releases. The current serialization support is\n appropriate for short term storage or RMI between applications running\n the same version of Swing.  As of 1.4, support for long term storage\n of all JavaBeans\u2122\n has been added to the java.beans package.\n Please see XMLEncoder.", "codes": ["protected class JTree.TreeSelectionRedirector\nextends Object\nimplements Serializable, TreeSelectionListener"], "fields": [], "methods": [{"method_name": "valueChanged", "method_sig": "public void valueChanged (TreeSelectionEvent e)", "description": "Invoked by the TreeSelectionModel when the\n selection changes."}]}