{"name": "Class LocatorImpl", "module": "java.xml", "package": "org.xml.sax.helpers", "text": "Provide an optional convenience implementation of Locator.\n\n \nThis module, both source code and documentation, is in the\n Public Domain, and comes with NO WARRANTY.\n See http://www.saxproject.org\n for further information.\n \nThis class is available mainly for application writers, who\n can use it to make a persistent snapshot of a locator at any\n point during a document parse:\n\n Locator locator;\n Locator startloc;\n\n public void setLocator (Locator locator)\n {\n         // note the locator\n   this.locator = locator;\n }\n\n public void startDocument ()\n {\n         // save the location of the start of the document\n         // for future use.\n   Locator startloc = new LocatorImpl(locator);\n }\n\nNormally, parser writers will not use this class, since it\n is more efficient to provide location information only when\n requested, rather than constantly updating a Locator object.", "codes": ["public class LocatorImpl\nextends Object\nimplements Locator"], "fields": [], "methods": [{"method_name": "getPublicId", "method_sig": "public String getPublicId()", "description": "Return the saved public identifier."}, {"method_name": "getSystemId", "method_sig": "public String getSystemId()", "description": "Return the saved system identifier."}, {"method_name": "getLineNumber", "method_sig": "public int getLineNumber()", "description": "Return the saved line number (1-based)."}, {"method_name": "getColumnNumber", "method_sig": "public int getColumnNumber()", "description": "Return the saved column number (1-based)."}, {"method_name": "setPublicId", "method_sig": "public void setPublicId (String publicId)", "description": "Set the public identifier for this locator."}, {"method_name": "setSystemId", "method_sig": "public void setSystemId (String systemId)", "description": "Set the system identifier for this locator."}, {"method_name": "setLineNumber", "method_sig": "public void setLineNumber (int lineNumber)", "description": "Set the line number for this locator (1-based)."}, {"method_name": "setColumnNumber", "method_sig": "public void setColumnNumber (int columnNumber)", "description": "Set the column number for this locator (1-based)."}]}