{"name": "Class LogStream", "module": "java.rmi", "package": "java.rmi.server", "text": "LogStream provides a mechanism for logging errors that are\n of possible interest to those monitoring a system.", "codes": ["@Deprecated\npublic class LogStream\nextends PrintStream"], "fields": [{"field_name": "SILENT", "field_sig": "public static final\u00a0int SILENT", "description": "log level constant (no logging)."}, {"field_name": "BRIEF", "field_sig": "public static final\u00a0int BRIEF", "description": "log level constant (brief logging)."}, {"field_name": "VERBOSE", "field_sig": "public static final\u00a0int VERBOSE", "description": "log level constant (verbose logging)."}], "methods": [{"method_name": "log", "method_sig": "@Deprecated\npublic static LogStream log (String name)", "description": "Return the LogStream identified by the given name.  If\n a log corresponding to \"name\" does not exist, a log using\n the default stream is created."}, {"method_name": "getDefaultStream", "method_sig": "@Deprecated\npublic static PrintStream getDefaultStream()", "description": "Return the current default stream for new logs."}, {"method_name": "setDefaultStream", "method_sig": "@Deprecated\npublic static void setDefaultStream (PrintStream newDefault)", "description": "Set the default stream for new logs."}, {"method_name": "getOutputStream", "method_sig": "@Deprecated\npublic OutputStream getOutputStream()", "description": "Return the current stream to which output from this log is sent."}, {"method_name": "setOutputStream", "method_sig": "@Deprecated\npublic void setOutputStream (OutputStream out)", "description": "Set the stream to which output from this log is sent."}, {"method_name": "write", "method_sig": "@Deprecated\npublic void write (int b)", "description": "Write a byte of data to the stream.  If it is not a newline, then\n the byte is appended to the internal buffer.  If it is a newline,\n then the currently buffered line is sent to the log's output\n stream, prefixed with the appropriate logging information."}, {"method_name": "write", "method_sig": "@Deprecated\npublic void write (byte[] b,\n                  int off,\n                  int len)", "description": "Write a subarray of bytes.  Pass each through write byte method."}, {"method_name": "toString", "method_sig": "@Deprecated\npublic String toString()", "description": "Return log name as string representation."}, {"method_name": "parseLevel", "method_sig": "@Deprecated\npublic static int parseLevel (String s)", "description": "Convert a string name of a logging level to its internal\n integer representation."}]}