{"name": "Interface NewTree", "module": "jdk.scripting.nashorn", "package": "jdk.nashorn.api.tree", "text": "A tree node to declare a new instance of a class.\n\n For example:\n \n   new identifier ( )\n\n   new identifier ( arguments )\n ", "codes": ["@Deprecated(since=\"11\",\n            forRemoval=true)\npublic interface NewTree\nextends ExpressionTree"], "fields": [], "methods": [{"method_name": "getConstructorExpression", "method_sig": "ExpressionTree getConstructorExpression()", "description": "Returns the constructor expression of this 'new' expression."}]}