{"name": "Interface PublicKey", "module": "java.base", "package": "java.security", "text": "A public key. This interface contains no methods or constants.\n It merely serves to group (and provide type safety for) all public key\n interfaces.\n\n Note: The specialized public key interfaces extend this interface.\n See, for example, the DSAPublicKey interface in\n java.security.interfaces.", "codes": ["public interface PublicKey\nextends Key"], "fields": [{"field_name": "serialVersionUID", "field_sig": "static final\u00a0long serialVersionUID", "description": "The class fingerprint that is set to indicate serialization\n compatibility with a previous version of the class."}], "methods": []}