{"name": "Class RecordedClass", "module": "jdk.jfr", "package": "jdk.jfr.consumer", "text": "A recorded Java type, such as a class or an interface.", "codes": ["public final class RecordedClass\nextends RecordedObject"], "fields": [], "methods": [{"method_name": "getModifiers", "method_sig": "public int getModifiers()", "description": "Returns the modifiers of the class.\n \n See Modifier"}, {"method_name": "getClassLoader", "method_sig": "public RecordedClassLoader getClassLoader()", "description": "Returns the class loader that defined the class.\n \n If the bootstrap class loader is represented as null in the Java\n Virtual Machine (JVM), then null is also the return value of this method."}, {"method_name": "getName", "method_sig": "public String getName()", "description": "Returns the fully qualified name of the class (for example,\n \"java.lang.String\")."}, {"method_name": "getId", "method_sig": "public long getId()", "description": "Returns a unique ID for the class.\n \n The ID might not be the same between Java Virtual Machine (JVM) instances."}]}