{"name": "Class ServerRuntimeException", "module": "java.rmi", "package": "java.rmi", "text": "From a server executing on JDK\u00a01.1, a\n ServerRuntimeException is thrown as a result of a\n remote method invocation when a RuntimeException is\n thrown while processing the invocation on the server, either while\n unmarshalling the arguments, executing the remote method itself, or\n marshalling the return value.\n\n A ServerRuntimeException instance contains the original\n RuntimeException that occurred as its cause.\n\n A ServerRuntimeException is not thrown from servers\n executing on the Java 2 platform v1.2 or later versions.", "codes": ["@Deprecated\npublic class ServerRuntimeException\nextends RemoteException"], "fields": [], "methods": []}