{"name": "Class TimeLimitExceededException", "module": "java.naming", "package": "javax.naming", "text": "This exception is thrown when a method\n does not terminate within the specified time limit.\n This can happen, for example, if the user specifies that\n the method should take no longer than 10 seconds, and the\n method fails to complete with 10 seconds.\n\n  Synchronization and serialization issues that apply to NamingException\n apply directly here.", "codes": ["public class TimeLimitExceededException\nextends LimitExceededException"], "fields": [], "methods": []}