{"name": "Interface XMLValidateContext", "module": "java.xml.crypto", "package": "javax.xml.crypto.dsig", "text": "Contains context information for validating XML Signatures. This interface\n is primarily intended for type-safety.\n\n Note that XMLValidateContext instances can contain\n information and state specific to the XML signature structure it is\n used with. The results are unpredictable if an\n XMLValidateContext is used with different signature structures\n (for example, you should not use the same XMLValidateContext\n instance to validate two different XMLSignature objects).\n \nSupported Properties\nThe following properties can be set by an application using the\n setProperty method.\n \njavax.xml.crypto.dsig.cacheReference: value must be a\n      Boolean. This property controls whether or not the\n      Reference.validate method will cache the\n      dereferenced content and pre-digested input for subsequent retrieval via\n      the Reference.getDereferencedData\n      and Reference.getDigestInputStream methods. The default value if not\n      specified is Boolean.FALSE.\n ", "codes": ["public interface XMLValidateContext\nextends XMLCryptoContext"], "fields": [], "methods": []}